<?xml version="1.0" encoding="UTF-8" ?>
<stf:setup xmlns:stf="http://glacier.lbl.gov/icecube/daq/stf"
  xmlns:xsi="http://www.w3.org/2001/XMLSchema-instance"
  xsi:schemaLocation="http://glacier.lbl.gov/icecube/daq/stf file:/Volumes/IceCube/WorkSpaces/jas-1/xml/daq/stf.xsd">

 <atwd_pulser>
  <parameters>
   <atwd_sampling_speed_dac>2000</atwd_sampling_speed_dac>
   <atwd_ramp_top_dac>2400</atwd_ramp_top_dac>
   <atwd_ramp_bias_dac>350</atwd_ramp_bias_dac>
   <atwd_analog_ref_dac>2300</atwd_analog_ref_dac>
   <atwd_pedestal_dac>2200</atwd_pedestal_dac>
   <atwd_chip_a_or_b>0</atwd_chip_a_or_b>
   <atwd_channel>0</atwd_channel>
   <atwd_trig_forced_or_spe>0</atwd_trig_forced_or_spe>
   <pedestal_subtraction>True</pedestal_subtraction>
   <spe_discriminator_uvolt>0</spe_discriminator_uvolt>
   <pulse_delay_wrt_launch></pulse_delay_wrt_launch>
   <loop_count>1000</loop_count>
  </parameters>
 </atwd_pulser>
</stf:setup>
