<?xml version="1.0" encoding="UTF-8"?>
<stf:test xmlns:stf="http://glacier.lbl.gov/icecube/daq/stf">
  <name>ADC</name>
  <description>ADC Tests</description>
  <version major="1" minor="0"/>
  <inputParameter>
    <description>Selects one of the ADC chips on the board (0 = CS0 and 1 = CS1)</description>
    <name>adc_chip</name>
    <unsignedInt default="0" maxValue="0" minValue="0"/>
  </inputParameter>

  <inputParameter>
    <description>Selects one of the channels of the ADC chip to be read out</description>
    <name>adc_channel</name>
    <unsignedInt default="0" maxValue="7" minValue="0"/>
  </inputParameter>

  <inputParameter>
    <description>Number of ADC values to acquire to compute a mean and spread</description>
    <name>loop_count</name>
    <unsignedInt default="1000" maxValue="1000000" minValue="1"/>
  </inputParameter>

  <outputParameter>
    <description>Mean of the ADC values distribution in count units</description>
    <name>adc_mean_counts</name>
    <unsignedInt/>
  </outputParameter>

  <outputParameter>
    <description>Spread of the ADC values distribution in count units</description>
    <name>adc_rms_counts</name>
    <unsignedInt/>
  </outputParameter>

  <outputParameter>
    <description>Maximum ADC value read in count units</description>
    <name>adc_max_counts</name>
    <unsignedInt/>
  </outputParameter>

  <outputParameter>
    <description>Minimum ADC value read in count units</description>
    <name>adc_min_counts</name>
    <unsignedInt/>
  </outputParameter>

  <outputParameter>
    <description>Mean of the ADC values distribution in millivolts or milliamp units</description>
    <name>adc_mean_mvolt_or_mamp</name>
    <unsignedInt/>
  </outputParameter>

  <outputParameter>
    <description>Spread of the ADC values distribution in millivolts or milliamp units</description>
    <name>adc_rms_mvolt_or_mamp</name>
    <unsignedInt/>
  </outputParameter>

  <outputParameter>
    <description>Maximum ADC value read in milivolts or miliamp units</description>
    <name>adc_max_mvolt_or_mamp</name>
    <unsignedInt/>
  </outputParameter>

  <outputParameter>
    <description>Minimum ADC value read in millivolts or milliamp units</description>
    <name>adc_min_mvolt_or_mamp</name>
    <unsignedInt/>
  </outputParameter>

</stf:test>








